indra/__init__.py
indra/config.py
indra/java_vm.py
indra/assemblers/__init__.py
indra/assemblers/cx/__init__.py
indra/assemblers/cx/assembler.py
indra/assemblers/cx/hub_layout.py
indra/assemblers/cyjs/__init__.py
indra/assemblers/cyjs/assembler.py
indra/assemblers/english/__init__.py
indra/assemblers/english/assembler.py
indra/assemblers/graph/__init__.py
indra/assemblers/graph/assembler.py
indra/assemblers/html/__init__.py
indra/assemblers/html/assembler.py
indra/assemblers/html/templates/indra/statements_view.html
indra/assemblers/html/templates/indra/template.html
indra/assemblers/index_card/__init__.py
indra/assemblers/index_card/assembler.py
indra/assemblers/indranet/__init__.py
indra/assemblers/indranet/assembler.py
indra/assemblers/indranet/net.py
indra/assemblers/kami/__init__.py
indra/assemblers/kami/assembler.py
indra/assemblers/pybel/__init__.py
indra/assemblers/pybel/assembler.py
indra/assemblers/pysb/__init__.py
indra/assemblers/pysb/assembler.py
indra/assemblers/pysb/base_agents.py
indra/assemblers/pysb/bmi_wrapper.py
indra/assemblers/pysb/common.py
indra/assemblers/pysb/export.py
indra/assemblers/pysb/kappa_util.py
indra/assemblers/pysb/preassembler.py
indra/assemblers/pysb/sites.py
indra/assemblers/sbgn/__init__.py
indra/assemblers/sbgn/assembler.py
indra/assemblers/sif/__init__.py
indra/assemblers/sif/assembler.py
indra/assemblers/tsv/__init__.py
indra/assemblers/tsv/assembler.py
indra/belief/__init__.py
indra/belief/skl.py
indra/benchmarks/__init__.py
indra/benchmarks/benchmark_db_coverage.py
indra/benchmarks/benchmark_trips.py
indra/benchmarks/bioprocesses/__init__.py
indra/benchmarks/bioprocesses/__main__.py
indra/benchmarks/phosphorylations/__init__.py
indra/databases/__init__.py
indra/databases/biolookup_client.py
indra/databases/bioregistry_client.py
indra/databases/cbio_client.py
indra/databases/chebi_client.py
indra/databases/chembl_client.py
indra/databases/context_client.py
indra/databases/doid_client.py
indra/databases/drugbank_client.py
indra-1.24.0.dist-info/LICENSE
indra-1.24.0.dist-info/METADATA
indra-1.24.0.dist-info/WHEEL
indra-1.24.0.dist-info/entry_points.txt
indra-1.24.0.dist-info/top_level.txt
indra-1.24.0.dist-info/RECORD
