Metadata-Version: 2.2
Name: indra
Version: 1.24.0
Summary: Integrated Network and Dynamical Reasoning Assembler
Home-page: http://github.com/gyorilab/indra
Author: Benjamin Gyori
Author-email: b.gyori@northeastern.edu
Keywords: systems,biology,model,pathway,assembler,nlp,mechanism,biochemistry,network,big mechanism,bigmech,world modelers,communicating with computers,cwc,automated scientific discovery framework,asdf,automating scientific knowledge extraction,aske,panacea
Classifier: Development Status :: 4 - Beta
Classifier: Environment :: Console
Classifier: Intended Audience :: Science/Research
Classifier: License :: OSI Approved :: BSD License
Classifier: Programming Language :: Python :: 3.8
Classifier: Programming Language :: Python :: 3.9
Classifier: Programming Language :: Python :: 3.10
Classifier: Programming Language :: Python :: 3.11
Classifier: Programming Language :: Python :: 3.12
Classifier: Topic :: Scientific/Engineering :: Bio-Informatics
Classifier: Topic :: Scientific/Engineering :: Chemistry
Classifier: Topic :: Scientific/Engineering :: Mathematics
License-File: LICENSE
Requires-Dist: pysb>=1.3.0
Requires-Dist: objectpath
Requires-Dist: requests>=2.11
Requires-Dist: lxml
Requires-Dist: ipython
Requires-Dist: future
Requires-Dist: networkx>=3
Requires-Dist: pandas>=2
Requires-Dist: ndex2==2.0.1
Requires-Dist: jinja2
Requires-Dist: protmapper>=0.0.29
Requires-Dist: obonet
Requires-Dist: tqdm
Requires-Dist: pybiopax>=0.0.5
Provides-Extra: trips-offline
Requires-Dist: pykqml; extra == "trips-offline"
Provides-Extra: reach-offline
Requires-Dist: cython<3; extra == "reach-offline"
Requires-Dist: pyjnius==1.1.4; extra == "reach-offline"
Provides-Extra: eidos-offline
Requires-Dist: cython<3; extra == "eidos-offline"
Requires-Dist: pyjnius==1.1.4; extra == "eidos-offline"
Provides-Extra: hypothesis
Requires-Dist: gilda>1.0.0; extra == "hypothesis"
Provides-Extra: geneways
Requires-Dist: stemming; extra == "geneways"
Requires-Dist: nltk<3.6; extra == "geneways"
Provides-Extra: bel
Requires-Dist: pybel<0.16.0,>=0.15.0; extra == "bel"
Provides-Extra: sbml
Requires-Dist: python-libsbml; extra == "sbml"
Provides-Extra: machine
Requires-Dist: pytz; extra == "machine"
Requires-Dist: tzlocal; extra == "machine"
Requires-Dist: tweepy; extra == "machine"
Requires-Dist: pyyaml>=5.1.0; extra == "machine"
Requires-Dist: click; extra == "machine"
Provides-Extra: explanation
Requires-Dist: kappy==4.1.2; extra == "explanation"
Requires-Dist: paths-graph; extra == "explanation"
Provides-Extra: grounding
Requires-Dist: adeft; extra == "grounding"
Requires-Dist: gilda>1.0.0; extra == "grounding"
Provides-Extra: aws
Requires-Dist: boto3; extra == "aws"
Requires-Dist: reportlab; extra == "aws"
Provides-Extra: graph
Requires-Dist: pygraphviz; extra == "graph"
Provides-Extra: plot
Requires-Dist: matplotlib; extra == "plot"
Provides-Extra: isi
Requires-Dist: nltk<3.6; extra == "isi"
Requires-Dist: unidecode; extra == "isi"
Provides-Extra: api
Requires-Dist: flask<4.0,>=3.0; extra == "api"
Requires-Dist: flask_restx>=1.3.0; extra == "api"
Requires-Dist: flask_cors; extra == "api"
Requires-Dist: docstring-parser; extra == "api"
Requires-Dist: gunicorn; extra == "api"
Provides-Extra: sklearn-belief
Requires-Dist: scikit-learn<1.5.0; extra == "sklearn-belief"
Provides-Extra: owl
Requires-Dist: pronto; extra == "owl"
Provides-Extra: tests
Requires-Dist: pytest; extra == "tests"
Requires-Dist: pytest-cov; extra == "tests"
Requires-Dist: pynose; extra == "tests"
Provides-Extra: all
Requires-Dist: pygraphviz; extra == "all"
Requires-Dist: tweepy; extra == "all"
Requires-Dist: stemming; extra == "all"
Requires-Dist: pyyaml>=5.1.0; extra == "all"
Requires-Dist: pytest; extra == "all"
Requires-Dist: pytz; extra == "all"
Requires-Dist: nltk<3.6; extra == "all"
Requires-Dist: pybel<0.16.0,>=0.15.0; extra == "all"
Requires-Dist: pykqml; extra == "all"
Requires-Dist: cython<3; extra == "all"
Requires-Dist: unidecode; extra == "all"
Requires-Dist: scikit-learn<1.5.0; extra == "all"
Requires-Dist: click; extra == "all"
Requires-Dist: matplotlib; extra == "all"
Requires-Dist: pyjnius==1.1.4; extra == "all"
Requires-Dist: python-libsbml; extra == "all"
Requires-Dist: paths-graph; extra == "all"
Requires-Dist: adeft; extra == "all"
Requires-Dist: pronto; extra == "all"
Requires-Dist: boto3; extra == "all"
Requires-Dist: kappy==4.1.2; extra == "all"
Requires-Dist: pytest-cov; extra == "all"
Requires-Dist: reportlab; extra == "all"
Requires-Dist: pynose; extra == "all"
Requires-Dist: gunicorn; extra == "all"
Requires-Dist: gilda>1.0.0; extra == "all"
Requires-Dist: tzlocal; extra == "all"
Requires-Dist: docstring-parser; extra == "all"
Requires-Dist: flask<4.0,>=3.0; extra == "all"
Requires-Dist: flask_cors; extra == "all"
Requires-Dist: flask_restx>=1.3.0; extra == "all"
Dynamic: author
Dynamic: author-email
Dynamic: classifier
Dynamic: description
Dynamic: description-content-type
Dynamic: home-page
Dynamic: keywords
Dynamic: provides-extra
Dynamic: requires-dist
Dynamic: summary
